torrent_parser.py
torrent_parser-0.4.1.dist-info/LICENSE
torrent_parser-0.4.1.dist-info/METADATA
torrent_parser-0.4.1.dist-info/WHEEL
torrent_parser-0.4.1.dist-info/entry_points.txt
torrent_parser-0.4.1.dist-info/top_level.txt
torrent_parser-0.4.1.dist-info/RECORD
